{
  "$schema": "https://ui.shadcn.com/schema/registry-item.json",
  "name": "date-field",
  "dependencies": [
    "tailwind-variants",
    "@tabler/icons-react",
    "react-aria-components"
  ],
  "registryDependencies": [
    "http://localhost:3000/r/field",
    "utils"
  ],
  "files": [
    {
      "path": "components/ui/date-field.tsx",
      "content": "'use client'\n\nimport type { VariantProps } from 'tailwind-variants'\nimport { IconChevronDown } from '@tabler/icons-react'\nimport {\n  Button,\n  composeRenderProps,\n  type DateFieldProps,\n  type DateInputProps,\n  type DatePickerProps,\n  type DateRangePickerProps,\n  DateSegment,\n  type DateValue,\n  Group,\n  DateField as RACDateField,\n  DateInput as RACDateInput,\n  DatePicker as RACDatePicker,\n  DateRangePicker as RACDateRangePicker,\n  TimeField as RACTimeField,\n  type TimeFieldProps,\n  type TimeValue\n} from 'react-aria-components'\nimport { cn } from '@/lib/utils'\nimport { fieldVariants } from './field'\n\nconst DateField = <T extends DateValue>({\n  className,\n  orientation = 'vertical',\n  ...props\n}: DateFieldProps<T> & VariantProps<typeof fieldVariants>) => (\n  <RACDateField\n    className={composeRenderProps(className, (className) => cn(fieldVariants({ orientation }), className))}\n    data-orientation={orientation}\n    data-slot='field'\n    {...props}\n  />\n)\n\nconst TimeField = <T extends TimeValue>({\n  className,\n  orientation = 'vertical',\n  ...props\n}: TimeFieldProps<T> & VariantProps<typeof fieldVariants>) => (\n  <RACTimeField\n    className={composeRenderProps(className, (className) => cn(fieldVariants({ orientation }), className))}\n    data-orientation={orientation}\n    data-slot='field'\n    {...props}\n  />\n)\n\nconst DatePicker = <T extends DateValue>({\n  className,\n  orientation = 'vertical',\n  ...props\n}: DatePickerProps<T> & VariantProps<typeof fieldVariants>) => (\n  <RACDatePicker\n    className={composeRenderProps(className, (className) => cn(fieldVariants({ orientation }), className))}\n    data-orientation={orientation}\n    data-slot='field'\n    {...props}\n  />\n)\n\nconst DateRangePicker = <T extends DateValue>({\n  className,\n  orientation = 'vertical',\n  ...props\n}: DateRangePickerProps<T> & VariantProps<typeof fieldVariants>) => (\n  <RACDateRangePicker\n    className={composeRenderProps(className, (className) => cn(fieldVariants({ orientation }), className))}\n    data-orientation={orientation}\n    data-slot='field'\n    {...props}\n  />\n)\n\nconst DateInput = ({ className, ...props }: Omit<DateInputProps, 'children'>) => {\n  return (\n    <RACDateInput\n      className={composeRenderProps(className, (className) =>\n        cn(\n          'inline-flex w-full items-center justify-start',\n          'h-9 min-w-0 rounded-md border border-input bg-transparent px-3 py-1 text-base shadow-xs outline-none transition-[color,box-shadow,border] selection:bg-primary selection:text-primary-foreground disabled:pointer-events-none disabled:cursor-not-allowed disabled:opacity-50 md:text-sm dark:bg-input/30',\n          'hover:border-ring group-hover/field:border-ring data-focus-within:border-ring data-focus-within:ring-[3px] data-focus-within:ring-ring/50',\n          'aria-invalid:border-destructive aria-invalid:ring-destructive/20 dark:aria-invalid:ring-destructive/40',\n          className\n        )\n      )}\n      {...props}\n    >\n      {(segment) => (\n        <DateSegment\n          className='rounded-sm px-1 transition hover:ring hover:ring-ring/50 data-[placeholder=true]:data-focused:text-primary-foreground data-focused:bg-primary data-[type=literal]:p-0 data-[placeholder=true]:text-muted-foreground data-focused:text-primary-foreground data-focused:outline-hidden'\n          segment={segment}\n        />\n      )}\n    </RACDateInput>\n  )\n}\n\nconst DatePickerInput = ({ className, ...props }: Omit<DateInputProps, 'children'>) => {\n  return (\n    <Group\n      className={composeRenderProps(className, (className) =>\n        cn(\n          'group/input-group relative flex w-full items-center rounded-md border border-input shadow-xs outline-none transition-[color,box-shadow] dark:bg-input/30',\n          'h-9 w-full min-w-0 rounded-md border border-input bg-transparent py-1 text-base shadow-xs outline-none transition-[color,box-shadow] selection:bg-primary selection:text-primary-foreground disabled:pointer-events-none disabled:cursor-not-allowed disabled:opacity-50 md:text-sm dark:bg-input/30',\n          'in-data-open:border-ring in-data-open:ring-[3px] in-data-open:ring-ring/50',\n          'has-data-focus-within:border-ring has-data-focus-within:ring-[3px] has-data-focus-within:ring-ring/50',\n          'has-aria-invalid:border-destructive has-aria-invalid:ring-destructive/20 dark:has-aria-invalid:ring-destructive/40',\n          className\n        )\n      )}\n    >\n      <RACDateInput className={cn('inline-flex items-center justify-start px-3')} {...props}>\n        {(segment) => (\n          <DateSegment\n            className='rounded-sm px-1 data-[placeholder=true]:data-focused:text-primary-foreground data-focused:bg-primary data-[type=literal]:p-0 data-[placeholder=true]:text-muted-foreground data-focused:text-primary-foreground data-focused:outline-hidden'\n            segment={segment}\n          />\n        )}\n      </RACDateInput>\n      <Button\n        className={cn(\n          'touch-target ml-auto grid place-content-center outline-hidden',\n          'text-muted-foreground hover:text-foreground focus-visible:text-foreground data-pressed:text-foreground',\n          'px-[calc(--spacing(3.5)-1px)] py-[calc(--spacing(2.5)-1px)] sm:px-[calc(--spacing(3)-1px)] sm:py-[calc(--spacing(1.5)-1px)] sm:text-sm/6'\n        )}\n        data-slot='date-picker-trigger'\n      >\n        <IconChevronDown className='size-4 shrink-0' />\n      </Button>\n    </Group>\n  )\n}\n\nconst DateRangePickerInput = ({ className, ...props }: Omit<DateInputProps, 'children'>) => {\n  return (\n    <Group\n      className={composeRenderProps(className, (className) =>\n        cn(\n          'group/input-group relative flex w-full items-center rounded-md border border-input shadow-xs outline-none transition-[color,box-shadow] dark:bg-input/30',\n          'h-9 w-full min-w-0 rounded-md border border-input bg-transparent py-1 text-base shadow-xs outline-none transition-[color,box-shadow] selection:bg-primary selection:text-primary-foreground disabled:pointer-events-none disabled:cursor-not-allowed disabled:opacity-50 md:text-sm dark:bg-input/30',\n          'in-data-open:border-ring in-data-open:ring-[3px] in-data-open:ring-ring/50',\n          'has-data-focus-within:border-ring has-data-focus-within:ring-[3px] has-data-focus-within:ring-ring/50',\n          'has-aria-invalid:border-destructive has-aria-invalid:ring-destructive/20 dark:has-aria-invalid:ring-destructive/40',\n          className\n        )\n      )}\n    >\n      <RACDateInput className={cn('inline-flex items-center justify-start px-3')} slot='start' {...props}>\n        {(segment) => (\n          <DateSegment\n            className='rounded-sm px-1 data-[placeholder=true]:data-focused:text-primary-foreground data-focused:bg-primary data-[type=literal]:p-0 data-[placeholder=true]:text-muted-foreground data-focused:text-primary-foreground data-focused:outline-hidden'\n            segment={segment}\n          />\n        )}\n      </RACDateInput>\n      <span\n        aria-hidden='true'\n        className='pointer-events-none z-10 -mx-3 block h-0.5 w-2 shrink-0 self-center rounded-full bg-foreground group-disabled/date-range-picker:text-opacity-50 sm:-mx-2'\n      />\n      <RACDateInput className={cn('inline-flex items-center justify-start px-3')} slot='end' {...props}>\n        {(segment) => (\n          <DateSegment\n            className='rounded-sm px-1 data-[placeholder=true]:data-focused:text-primary-foreground data-focused:bg-primary data-[type=literal]:p-0 data-[placeholder=true]:text-muted-foreground data-focused:text-primary-foreground data-focused:outline-hidden'\n            segment={segment}\n          />\n        )}\n      </RACDateInput>\n      <Button\n        className={cn(\n          'touch-target ml-auto grid place-content-center outline-hidden',\n          'text-muted-foreground hover:text-foreground focus-visible:text-foreground data-pressed:text-foreground',\n          'px-[calc(--spacing(3.5)-1px)] py-[calc(--spacing(2.5)-1px)] sm:px-[calc(--spacing(3)-1px)] sm:py-[calc(--spacing(1.5)-1px)] sm:text-sm/6'\n        )}\n        data-slot='date-picker-trigger'\n      >\n        <IconChevronDown className='size-4 shrink-0' />\n      </Button>\n    </Group>\n  )\n}\n\nexport { DateInput, DatePickerInput, DateRangePickerInput, DateField, TimeField, DatePicker, DateRangePicker }\n",
      "type": "registry:ui"
    }
  ],
  "type": "registry:ui"
}